noteblog/__init__.py
noteblog/blog/__init__.py
noteblog/blog/typecho/__init__.py
noteblog/blog/typecho/log.py
noteblog/blog/typecho/main.py
noteblog/blog/typecho/models.py
noteblog/blog/typecho/core/__init__.py
noteblog/blog/typecho/core/core.py
noteblog/blog/typecho/core/entry.py
noteblog/blog/typecho/core/log.py
noteblog/blog/yuque/__init__.py
noteblog/blog/yuque/base.py
noteblog/blog/yuque/core.py
noteblog/core/__init__.py
noteblog/core/bak.py
noteblog/core/base.py
noteblog/core/meta.py
noteblog/publish/__init__.py
noteblog/publish/core.py
noteblog/publish/typecho.py
noteblog-0.5.7.dist-info/METADATA
noteblog-0.5.7.dist-info/WHEEL
noteblog-0.5.7.dist-info/top_level.txt
noteblog-0.5.7.dist-info/RECORD
