Metadata-Version: 2.1
Name: noteblog
Version: 0.5.7
Summary: noteblog
Home-page: https://github.com/1007530194
Author: niult
Author-email: 1007530194@qq.com
License: UNKNOWN
Platform: UNKNOWN
Requires-Dist: notebuild
Requires-Dist: notedata
